dguard_vad/__init__.py
dguard_vad/cli.py
dguard_vad/dguard_vad.py
dguard_vad/frame_queue.py
dguard_vad/pickable_session.py
dguard_vad/utils.py
dguad_vad-0.1.0.dist-info/LICENSE
dguad_vad-0.1.0.dist-info/METADATA
dguad_vad-0.1.0.dist-info/WHEEL
dguad_vad-0.1.0.dist-info/entry_points.txt
dguad_vad-0.1.0.dist-info/top_level.txt
dguad_vad-0.1.0.dist-info/RECORD
