Metadata-Version: 2.1
Name: dguad_vad
Version: 0.1.0
Home-page: 
Author: Zhao Sheng
Author-email: zhaosheng@nuaa.edu.cn
Classifier: Programming Language :: Python :: 3
Classifier: Operating System :: OS Independent
Classifier: Topic :: Scientific/Engineering
License-File: LICENSE
Requires-Dist: librosa
Requires-Dist: numpy
Requires-Dist: onnxruntime
Requires-Dist: soxr
Requires-Dist: praat-parselmouth
Requires-Dist: pyrnnoise
